trellocli/__init__.py
trellocli/__main__.py
trellocli/trelloservice.py
trello_cli_kit-1.1.0.dist-info/LICENSE
trello_cli_kit-1.1.0.dist-info/METADATA
trello_cli_kit-1.1.0.dist-info/WHEEL
trello_cli_kit-1.1.0.dist-info/entry_points.txt
trello_cli_kit-1.1.0.dist-info/top_level.txt
trello_cli_kit-1.1.0.dist-info/RECORD
