Metadata-Version: 2.1
Name: trello-cli-kit
Version: 1.1.0
Summary: Modify your Trello boards from your computer's command line
Author-email: Elaine Chan <elaineyunru.chan@gmail.com>
Project-URL: Homepage, https://github.com/elainechan01/trello-cli-kit
Classifier: Programming Language :: Python :: 3
Classifier: License :: OSI Approved :: MIT License
Classifier: Operating System :: OS Independent
Requires-Python: >=3.7
License-File: LICENSE
Requires-Dist: pytest ~=7.4.0
Requires-Dist: pytest-mock ~=3.11.1
Requires-Dist: py-trello ~=0.19.0
Requires-Dist: python-dotenv ~=1.0.0
Requires-Dist: cli-test-helpers ~=3.4.0
Requires-Dist: typer ~=0.9.0
Requires-Dist: rich ~=13.4.2
Requires-Dist: simple-term-menu ~=1.6.1
